{
  "agentId": "pm",
  "taskId": "development-pm-c31",
  "timestamp": "2026-04-07T05:28:07.910Z",
  "status": "success",
  "summary": "Product progress review completed for Cycle 31. Reviewed TASK-058 (Add progress indicators with Ora and Chalk) — ACCEPTED as production-ready. Implementation exceeds expectations with excellent code quality, comprehensive tests (41 tests), and strong product vision alignment. No scope gaps identified. Recommended next steps: Developer to start TASK-059 (verbose flag), QA to start TASK-060 (CLI integration tests). Detailed findings documented in pm-report-development-pm-c31.md.",
  "branchName": "agent/pm/development-pm-c31"
}
