{
  "agentId": "pm",
  "taskId": "development-pm-c23",
  "timestamp": "2026-04-07T02:59:15.664Z",
  "status": "success",
  "summary": "Validated TASK-107 (metrics module) - all acceptance criteria met. Implementation delivers 4 metric dimensions (execution time, memory, tokens, complexity) with 104 passing tests. Approved for release. Identified 2 scope gaps: metrics documentation (new STORY-015 recommended) and need to verify 5 blocked tasks. Critical finding: backlog sync broken (only 1/10 completed tasks reflected).",
  "branchName": "agent/pm/development-pm-c23"
}
